cruft_helloworld/__init__.py
cruft_helloworld/app.py
cruft_helloworld/py.typed
cruft_helloworld/services/__init__.py
cruft_helloworld/services/globe_emoji_with_geoip.py
cruft_helloworld/tools/__init__.py
cruft_helloworld/tools/config_loggers.py
cruft_helloworld/tools/dict_nested_update.py
cruft_helloworld/tools/enums.py
cruft_helloworld-0.4.2.dist-info/entry_points.txt
cruft_helloworld-0.4.2.dist-info/LICENSE
cruft_helloworld-0.4.2.dist-info/WHEEL
cruft_helloworld-0.4.2.dist-info/METADATA
cruft_helloworld-0.4.2.dist-info/RECORD
