Metadata-Version: 2.1
Name: cruft-helloworld
Version: 0.4.2
Summary: Cruft Python Hello-World
Home-page: https://github.com/yoyonel/cruft_helloworld
License: BSD-3-Clause
Author: lionel atty
Author-email: yoyonel@hotmail.com
Requires-Python: >=3.6.9,<4.0
Classifier: Development Status :: 4 - Beta
Classifier: Environment :: Web Environment
Classifier: Intended Audience :: Developers
Classifier: License :: OSI Approved :: BSD License
Classifier: Operating System :: OS Independent
Classifier: Programming Language :: Python
Classifier: Programming Language :: Python :: 3
Classifier: Programming Language :: Python :: 3.6
Classifier: Programming Language :: Python :: 3.7
Classifier: Programming Language :: Python :: 3.8
Classifier: Programming Language :: Python :: 3.9
Classifier: Topic :: Software Development :: Libraries :: Python Modules
Classifier: Typing :: Typed
Requires-Dist: Cython (>=0.29.21,<0.30.0)
Requires-Dist: click (>=7.1.2,<8.0.0)
Requires-Dist: click-default-group (>=1.2.2,<2.0.0)
Requires-Dist: colorlog (>=4.6.2,<5.0.0)
Requires-Dist: pyfiglet (>=0.8.post1,<0.9)
Requires-Dist: python-geoip-geolite2 (>=2015.0303,<2016.0)
Requires-Dist: python-geoip-python3 (>=1.3,<2.0)
Requires-Dist: requests (>=2.25.1,<3.0.0)
Requires-Dist: rich (>=9.4.0,<10.0.0)
Project-URL: Documentation, https://github.com/yoyonel/cruft_helloworld/blob/master/README.md
Project-URL: Repository, https://github.com/yoyonel/cruft_helloworld
